panoptic/__init__.py
panoptic/cli.py
panoptic/dateformat.py
panoptic/main.py
panoptic/utils.py
panoptic/assets/arrow.png
panoptic/core/__init__.py
panoptic/core/exporter.py
panoptic/core/panoptic.py
panoptic/core/panoptic_server.py
panoptic/core/db/__init__.py
panoptic/core/db/create.py
panoptic/core/db/db.py
panoptic/core/db/db_connection.py
panoptic/core/db/utils.py
panoptic/core/db/migrations/v3.py
panoptic/core/db/migrations/v4.py
panoptic/core/db/migrations/v5.py
panoptic/core/db/migrations/v6.py
panoptic/core/db/migrations/v7.py
panoptic/core/importer/__init__.py
panoptic/core/importer/importer.py
panoptic/core/importer/parsing.py
panoptic/core/panoptic_db/create.py
panoptic/core/panoptic_db/db_connection.py
panoptic/core/panoptic_db/panoptic_db.py
panoptic/core/plugin/__init__.py
panoptic/core/plugin/plugin.py
panoptic/core/plugin/plugin_project_interface.py
panoptic/core/project/__init__.py
panoptic/core/project/plugin_watcher.py
panoptic/core/project/project.py
panoptic/core/project/project_actions.py
panoptic/core/project/project_db.py
panoptic/core/project/project_events.py
panoptic/core/project/project_ui.py
panoptic/core/project/undo_queue.py
panoptic/core/task/__init__.py
panoptic/core/task/import_image_task.py
panoptic/core/task/import_instance_task.py
panoptic/core/task/load_plugin_task.py
panoptic/core/task/task.py
panoptic/core/task/task_queue.py
panoptic/html/favicon.ico
panoptic/html/index.html
panoptic/html/assets/HomeView-B6FzlBsb.css
panoptic/html/assets/HomeView-BV5-4TiU.js
panoptic/html/assets/ProjectView-C9U9hN1l.css
panoptic/html/assets/ProjectView-DBf3hzTo.js
panoptic/html/assets/TestView-Cn95LU20.js
panoptic/html/assets/TestView-D2o9eoja.css
panoptic/html/assets/Tutorial-D_fmIdFX.css
panoptic/html/assets/Tutorial.vue_vue_type_style_index_0_lang-BK-GAJtk.js
panoptic/html/assets/bootstrap-icons-BOrJxbIo.woff
panoptic/html/assets/bootstrap-icons-BtvjY1KL.woff2
panoptic/html/assets/duck-S9Uqeb_r.svg
panoptic/html/assets/index-B0LMNpRz.css
panoptic-0.7.1.dist-info/METADATA
panoptic-0.7.1.dist-info/WHEEL
panoptic-0.7.1.dist-info/entry_points.txt
panoptic-0.7.1.dist-info/RECORD
