Metadata-Version: 2.4
Name: panoptic
Version: 0.7.1
Summary: Explore and analyze large datasets of images
Project-URL: Repository, https://github.com/CERES-Sorbonne/panoptic
Project-URL: Documentation, https://github.com/CERES-Sorbonne/panoptic#readme
Project-URL: Issues, https://github.com/CERES-Sorbonne/panoptic/issues
Project-URL: Lab's website, https://ceres.sorbonne-universite.fr/
License-Expression: MPL-2.0
Keywords: Data visualization,Image analysis,Image clustering,Image corpora,Machine learning,Web application
Classifier: Development Status :: 4 - Beta
Classifier: Intended Audience :: Science/Research
Classifier: License :: OSI Approved :: Mozilla Public License 2.0 (MPL 2.0)
Classifier: Operating System :: OS Independent
Classifier: Programming Language :: Python
Classifier: Programming Language :: Python :: 3
Classifier: Programming Language :: Python :: 3.9
Classifier: Programming Language :: Python :: 3.10
Classifier: Programming Language :: Python :: 3.11
Classifier: Programming Language :: Python :: 3.12
Classifier: Programming Language :: Python :: Implementation :: CPython
Classifier: Programming Language :: Python :: Implementation :: PyPy
Requires-Python: >=3.10
Requires-Dist: aiofiles
Requires-Dist: aiosqlite
Requires-Dist: fastapi
Requires-Dist: fastapi-camelcase
Requires-Dist: imagehash
Requires-Dist: numpy
Requires-Dist: orjson
Requires-Dist: pendulum
Requires-Dist: pillow
Requires-Dist: polars
Requires-Dist: psutil
Requires-Dist: pydantic
Requires-Dist: pypika
Requires-Dist: python-multipart
Requires-Dist: python-socketio
Requires-Dist: requests
Requires-Dist: show-in-file-manager
Requires-Dist: starlette
Requires-Dist: uvicorn
Requires-Dist: watchfiles
Provides-Extra: vision
Requires-Dist: panopticml>=0.0.3; extra == 'vision'
